{"it": 1, "connect": 1, "this": 1, "out": 1, "do": 3, "center": 2, "write": 1, "mental": 1, "for": 1, "field": 1, "fourth": 1, "with": 2, "work": 2, "tend": 1, "of": 4, "themselv": 1, "would": 1, "while": 1, "floor": 1, "bio/chem/neuro": 1, "toward": 1, "situat": 1, "insid": 1, "research": 7, "everyth": 1, "chem": 1, "room": 1, "certain": 1, "kid": 2, "class": 2, "mindset": 1, "some": 3, "the": 10, "analyz": 2, "survey": 1, "more": 1, "on": 6, "depart": 2, "faun": 1, "fundament": 1, "thing": 1, "truest": 1, "as": 2, "one": 2, "send": 1, "time": 1, "theori": 3, "creepi": 1, "like": 1, "most": 1, "done": 1, "children": 1, "littl": 1, "interest": 1, "ton": 1, "lot": 1, "so": 1, "support": 1, "child": 2, "guid": 1, "conduct": 2, "disprov": 1, "behavior": 2, "total_words": 259, "stabl": 1, "guess": 1, "i": 4, "at": 1, "develop": 2, "to": 7, "$10": 1, "mind": 2, "your": 1, "arn": 1, "social": 1, "i'v": 1, "took": 1, "professor": 1, "what": 1, "or": 4, "have": 1, "whether": 1, "psychologist": 1, "studi": 11, "psyc": 1, "think": 2, "psycholog": 3, "them": 1, "find": 1, "anthro/socstudi": 1, "mean": 1, "project": 1, "take": 2, "read": 2, "they": 6, "chemic": 1, "advertis": 1, "a": 4, "peopl": 6, "i'm": 1, "paper": 1, "action": 1, "about": 4, "way": 2, "and": 10, "review": 1, "but": 1, "101": 1, "student": 2, "in": 5, "over": 1, "current": 1, "perhap": 1, "peop": 1, "particip": 1, "learn": 1, "brain": 1, "probabl": 2, "how": 4, "that": 3, "help": 1, "basi": 1, "know": 1, "statist": 2, "understand": 1, "pay": 2, "focus": 2, "these": 1, "own": 1, "than": 1, "manifest": 1, "disord": 1, "email": 1, "ill": 1, "selv": 1, "also": 2, "famous": 2, "friend": 1, "tri": 1, "diagnos": 1, "somehow": 1, "their": 5, "anyth": 1, "result": 1}